mdast_cli_core/__init__.py
mdast_cli_core/api.py
mdast_cli_core/base.py
mdast_cli_core/token.py
mdast_cli_core-2023.8.2.dist-info/METADATA
mdast_cli_core-2023.8.2.dist-info/WHEEL
mdast_cli_core-2023.8.2.dist-info/top_level.txt
mdast_cli_core-2023.8.2.dist-info/RECORD
