Metadata-Version: 2.1
Name: mdast-cli-core
Version: 2023.8.2
Summary: mDast core package
Home-page: https://github.com/Dynamic-Mobile-Security/mdast-cli-core
Author: Dynamic-Mobile-Security
Classifier: Programming Language :: Python :: 3
Classifier: License :: OSI Approved :: MIT License
Classifier: Operating System :: Unix
Requires-Dist: requests >2.20
